devautotools/__init__.py
devautotools/__main__.py
devautotools/_django.py
devautotools/_docker.py
devautotools/_env.py
devautotools/_tempfile.py
devautotools/_utils.py
devautotools/_venv.py
devautotools/_venvctrl.py
devautotools-1.2.0.dist-info/licenses/LICENSE
devautotools-1.2.0.dist-info/METADATA
devautotools-1.2.0.dist-info/WHEEL
devautotools-1.2.0.dist-info/top_level.txt
devautotools-1.2.0.dist-info/RECORD
