Metadata-Version: 2.4
Name: devautotools
Version: 1.2.0
Summary: Developers automated tools
Author-email: Irving Leonard <irvingleonard@gmail.com>
License: BSD 3-Clause "New" or "Revised" License
Project-URL: homepage, https://github.com/irvingleonard/devautotools
Project-URL: repository, https://github.com/irvingleonard/devautotools.git
Keywords: devtools,venvtools,docker
Classifier: Development Status :: 4 - Beta
Classifier: Environment :: Console
Classifier: Intended Audience :: Developers
Classifier: Intended Audience :: End Users/Desktop
Classifier: License :: OSI Approved :: BSD License
Classifier: Natural Language :: English
Classifier: Operating System :: OS Independent
Classifier: Programming Language :: Python
Classifier: Programming Language :: Python :: 3
Classifier: Topic :: Utilities
Requires-Python: >=3.9
License-File: LICENSE
Requires-Dist: pip
Requires-Dist: simplifiedapp
Requires-Dist: tomli
Provides-Extra: dev
Requires-Dist: coverage; extra == "dev"
Dynamic: description
Dynamic: license-file
Dynamic: summary
